sqlsynthgen/__init__.py
sqlsynthgen/base.py
sqlsynthgen/create.py
sqlsynthgen/json_schemas/config_schema.json
sqlsynthgen/main.py
sqlsynthgen/make.py
sqlsynthgen/providers.py
sqlsynthgen/remove.py
sqlsynthgen/settings.py
sqlsynthgen/templates/ssg.py.j2
sqlsynthgen/unique_generator.py
sqlsynthgen/utils.py
sqlsynthgen-0.4.2.dist-info/LICENSE
sqlsynthgen-0.4.2.dist-info/METADATA
sqlsynthgen-0.4.2.dist-info/WHEEL
sqlsynthgen-0.4.2.dist-info/entry_points.txt
sqlsynthgen-0.4.2.dist-info/RECORD
